pyechonext/__init__.py
pyechonext/apidoc_ui/__init__.py
pyechonext/apidoc_ui/api_documentation.py
pyechonext/apidoc_ui/ui.py
pyechonext/app.py
pyechonext/auth/__init__.py
pyechonext/auth/base.py
pyechonext/auth/jwt_auth.py
pyechonext/cache.py
pyechonext/config.py
pyechonext/docsgen/__init__.py
pyechonext/docsgen/document.py
pyechonext/docsgen/projgen.py
pyechonext/logging/__init__.py
pyechonext/logging/logger.py
pyechonext/middleware.py
pyechonext/mvc/controllers.py
pyechonext/mvc/models.py
pyechonext/mvc/routes.py
pyechonext/mvc/views.py
pyechonext/permissions.py
pyechonext/request.py
pyechonext/response.py
pyechonext/security/crypts.py
pyechonext/security/defence.py
pyechonext/security/hashing.py
pyechonext/static.py
pyechonext/template_engine/__init__.py
pyechonext/template_engine/builtin.py
pyechonext/template_engine/jinja.py
pyechonext/urls.py
pyechonext/utils/__init__.py
pyechonext/utils/exceptions.py
pyechonext/utils/patterns.py
pyechonext/utils/performance.py
pyechonext/utils/slugger.py
pyechonext/utils/stack.py
pyechonext/utils/trie.py
pyechonext-0.7.18.dist-info/LICENSE
pyechonext-0.7.18.dist-info/METADATA
pyechonext-0.7.18.dist-info/WHEEL
pyechonext-0.7.18.dist-info/RECORD
