Metadata-Version: 2.3
Name: pyechonext
Version: 0.7.18
Summary: EchoNext is a lightweight, fast and scalable web framework for Python
License: LGPL-2.1
Author: alexeev-prog
Author-email: alexeev.dev@mail.ru
Requires-Python: >=3.12,<4.0
Classifier: License :: OSI Approved
Classifier: Programming Language :: Python :: 3
Classifier: Programming Language :: Python :: 3.12
Classifier: Programming Language :: Python :: 3.13
Requires-Dist: echonextdi (>=0.2.0,<0.3.0)
Requires-Dist: gunicorn (>=23.0,<24.0)
Requires-Dist: hermes-langlib (>=0.1.4,<0.2.0)
Requires-Dist: jinja2 (>=3.1,<4.0)
Requires-Dist: orjson (>=3.9,<4.0)
Requires-Dist: parse (>=1.20,<2.0)
Requires-Dist: pyjwt (>=2.10.1,<3.0.0)
Requires-Dist: pylint (>=3.3.7,<4.0.0)
Requires-Dist: pysocks (>=1.7,<2.0)
Requires-Dist: python-dotenv (>=1.0,<2.0)
Requires-Dist: pyyaml (>=6.0,<7.0)
Requires-Dist: requests (>=2.32,<3.0)
Requires-Dist: requests-wsgi-adapter (>=0.4,<0.5)
Requires-Dist: rich (>=14.0.0,<15.0.0)
Requires-Dist: structlog (>=25.4.0,<26.0.0)
Requires-Dist: toml (>=0.10,<0.11)
Requires-Dist: tqdm (>=4.67.1,<5.0.0)
Requires-Dist: ty (>=0.0.1a9,<0.0.2)
